{
    "issue_id": "AI-573",
    "fire_summary": "Development of backend APIs for savings goals management poses security risks due to potential collection and processing of sensitive financial data and customer information. The provision of test user credentials could be vulnerable to unauthorized access or misuse if not properly secured. APIs could expose sensitive information about application architecture and infrastructure. The ticket lacks information about transparency, feedback, or user control over personal data, which could lead to privacy concerns.",
    "recommendations": [
        {
            "concern": {
                "short_description": "Test user account might enable linking savings goals to identity",
                "long_description": "The use of a specific test user account (gabrieal12@archint.com) could potentially allow linking the user's savings goals and progress to their identity, leading to privacy concerns.",
                "methodology": {
                    "category": "Linkability",
                    "type": "Linddun"
                }
            },
            "recommendation": "Implement secure user authentication and authorization mechanisms, such as OAuth 2.0 or JSON Web Tokens (JWT), to protect user data and prevent unauthorized access. This will help maintain the privacy and security of users' savings goals and progress.",
            "controls": {
                "NIST": [
                    "SC-13",
                    "IA-05"
                ],
                "PCI": [
                    "6.5.4"
                ],
                "HITRUST": null,
                "CIS": null
            }
        },
        {
            "concern": {
                "short_description": "Identified test user account could enable user identification",
                "long_description": "The explicit mention of a specific test user account (gabrieal12@archint.com) could lead to the identification of the individual associated with that account, even if the account is not directly linked to the user's real identity.",
                "methodology": {
                    "category": "Identifiability",
                    "type": "Linddun"
                }
            },
            "recommendation": "Avoid including specific test user accounts in documentation. Instead, use generic placeholder values or instructions for creating test accounts. This helps protect the privacy of individual users and reduces the risk of unauthorized access or misuse.",
            "controls": {
                "NIST": [
                    "SC-13",
                    "IA-05"
                ],
                "PCI": [
                    "6.5.4"
                ],
                "HITRUST": null,
                "CIS": null
            }
        },
        {
            "concern": {
                "short_description": "Savings goals APIs might result in excessive data disclosure",
                "long_description": "The development of APIs for managing savings goals could lead to the excessive collection, storage, processing, or sharing of personal financial data, which could be considered a privacy concern.",
                "methodology": {
                    "category": "Disclosure of information",
                    "type": "Linddun"
                }
            },
            "recommendation": "Implement strict data minimization principles to ensure that only the minimum amount of personal financial data necessary for the savings goals management feature is collected and stored. Regularly review data requirements and remove any unnecessary information.",
            "controls": {
                "NIST": [
                    "SC-13",
                    "IA-05"
                ],
                "PCI": [
                    "6.5.4"
                ],
                "HITRUST": null,
                "CIS": null
            }
        },
        {
            "concern": {
                "short_description": "Lack of user awareness and control over data processing",
                "long_description": "The ticket does not mention any information about transparency, feedback, or user control over their personal data, which could lead to users being unaware of how their data is being processed.",
                "methodology": {
                    "category": "Unawareness",
                    "type": "Linddun"
                }
            },
            "recommendation": "Implement transparent data practices to ensure that users have clear visibility into how their personal data is being collected, processed, and used for the savings goals management feature. Provide detailed privacy policies and user controls to empower users and build trust.",
            "controls": {
                "NIST": [
                    "SC-13",
                    "IA-05"
                ],
                "PCI": [
                    "6.5.4"
                ],
                "HITRUST": null,
                "CIS": null
            }
        },
        {
            "concern": {
                "short_description": "Unaddressed compliance with data protection regulations",
                "long_description": "The ticket does not provide any information about the system's compliance with security and data management best practices, standards, or legislation, which could lead to privacy risks.",
                "methodology": {
                    "category": "Non-compliance",
                    "type": "Linddun"
                }
            },
            "recommendation": "Implement strong authentication and authorization mechanisms, such as multi-factor authentication and role-based access control, to protect against unauthorized access and data breaches. Ensure compliance with relevant data protection regulations.",
            "controls": {
                "NIST": [
                    "SC-13",
                    "IA-05"
                ],
                "PCI": [
                    "6.5.4"
                ],
                "HITRUST": null,
                "CIS": null
            }
        },
        {
            "concern": {
                "short_description": "APIs might collect sensitive financial data and customer info",
                "long_description": "The APIs developed could be used to collect sensitive financial data and customer information, which could be a security concern if not properly secured.",
                "methodology": {
                    "category": "Collection",
                    "type": "Mitre"
                }
            },
            "recommendation": "Implement robust authentication and authorization mechanisms to protect against unauthorized access. Use secure authentication protocols such as OAuth 2.0 or JSON Web Tokens (JWT), and role-based access controls to limit actions based on user permissions.",
            "controls": {
                "NIST": [
                    "SC-13",
                    "IA-05"
                ],
                "PCI": [
                    "6.5.4"
                ],
                "HITRUST": null,
                "CIS": null
            }
        },
        {
            "concern": {
                "short_description": "Test credentials could lead to unauthorized access",
                "long_description": "The test user and password provided could be a security concern if these credentials are not properly protected or if the APIs are not properly authenticated and authorized.",
                "methodology": {
                    "category": "Credential Access",
                    "type": "Mitre"
                }
            },
            "recommendation": "Implement secure authentication and authorization mechanisms using industry-standard protocols like OAuth 2.0 or JWT. Establish secure key management processes and role-based access controls to prevent test credentials from being misused.",
            "controls": {
                "NIST": [
                    "SC-13",
                    "IA-05"
                ],
                "PCI": [
                    "6.5.4"
                ],
                "HITRUST": null,
                "CIS": null
            }
        },
        {
            "concern": {
                "short_description": "APIs could potentially exfiltrate sensitive financial data",
                "long_description": "The APIs could be used to exfiltrate sensitive financial data and customer information if not properly secured.",
                "methodology": {
                    "category": "Exfiltration",
                    "type": "Mitre"
                }
            },
            "recommendation": "Enforce secure data transmission and storage by requiring HTTPS for all communications and implementing industry-standard encryption for sensitive data at rest. Establish comprehensive logging and monitoring to track API access and detect potential security incidents.",
            "controls": {
                "NIST": [
                    "SC-13",
                    "IA-05"
                ],
                "PCI": [
                    "6.5.4"
                ],
                "HITRUST": null,
                "CIS": null
            }
        },
        {
            "concern": {
                "short_description": "Test credentials could enable privilege escalation",
                "long_description": "The test user and password provided could be a security concern if they are not properly protected or if the APIs are not properly authenticated and authorized, potentially allowing privilege escalation.",
                "methodology": {
                    "category": "Privilege Escalation",
                    "type": "Mitre"
                }
            },
            "recommendation": "Implement secure authentication and authorization mechanisms such as OAuth 2.0 or JWT, establish secure token management processes, and implement role-based access control (RBAC) to authorize users based on their assigned permissions.",
            "controls": {
                "NIST": [
                    "SC-13",
                    "IA-05"
                ],
                "PCI": [
                    "6.5.4"
                ],
                "HITRUST": null,
                "CIS": null
            }
        },
        {
            "concern": {
                "short_description": "APIs might expose sensitive application details",
                "long_description": "The APIs could potentially expose information about the application's architecture, infrastructure, or other sensitive details that could be used by an attacker for further reconnaissance.",
                "methodology": {
                    "category": "Discovery",
                    "type": "Mitre"
                }
            },
            "recommendation": "Implement secure API design practices including HTTPS usage, input validation, and limiting exposure of sensitive data. Follow secure design principles and implement role-based access control to restrict access based on user roles and permissions.",
            "controls": {
                "NIST": [
                    "SC-13",
                    "IA-05"
                ],
                "PCI": [
                    "6.5.4"
                ],
                "HITRUST": null,
                "CIS": null
            }
        }
    ]
}