<gmd:scope>
    <gmd:DQ_Scope>
        <gmd:level>
            <!-- https://docs.geostandaarden.nl/md/mdprofiel-iso19119/#niveau-kwaliteitsbeschrijving -->
            <gmd:MD_ScopeCode codeList="https://standards.iso.org/iso/19139/resources/gmxCodelists.xml#MD_ScopeCode" codeListValue="service">service</gmd:MD_ScopeCode>
        </gmd:level>
        <gmd:levelDescription>
            <gmd:MD_ScopeDescription>
                <gmd:other>
                    <!-- https://docs.geostandaarden.nl/md/mdprofiel-iso19119/#niveau-kwaliteitsbeschrijving-naam -->
                    <gco:CharacterString>service</gco:CharacterString>
                </gmd:other>
            </gmd:MD_ScopeDescription>
        </gmd:levelDescription>
    </gmd:DQ_Scope>
</gmd:scope>
